lccgrid/__init__.py
lccgrid-0.1.3.dist-info/licenses/LICENSE
lccgrid-0.1.3.dist-info/METADATA
lccgrid-0.1.3.dist-info/WHEEL
lccgrid-0.1.3.dist-info/top_level.txt
lccgrid-0.1.3.dist-info/RECORD
