Metadata-Version: 2.4
Name: lccgrid
Version: 0.1.3
Summary: Convert Lambert Conformal grid to lat/lon coordinates
Author-email: phanpy <214837134+phanpy8910@users.noreply.github.com>
License: MIT License
Project-URL: Homepage, https://github.com/phanpy8910/lccgrid
Project-URL: Issues, https://github.com/phanpy/lccgrid/issues
Requires-Python: >=3.7
License-File: LICENSE
Requires-Dist: numpy
Requires-Dist: pyproj
Dynamic: license-file
